PyWireframe/__init__.py
PyWireframe/__main__.py
PyWireframe/engine.py
PyWireframe/render.py
PyWireframe-0.5.0.dist-info/LICENSE.txt
PyWireframe-0.5.0.dist-info/METADATA
PyWireframe-0.5.0.dist-info/WHEEL
PyWireframe-0.5.0.dist-info/top_level.txt
PyWireframe-0.5.0.dist-info/RECORD
