Metadata-Version: 2.1
Name: PyWireframe
Version: 0.5.0
Summary: PyreFrame is a wireframe 3D graphics engine which uses turtle graphics. It is highly inefficient, unrealistic, and does not support rotation of any kind.
Home-page: https://hyperhamster535.github.io/PyWireframe/
Author: HyperHamster534
Author-email: joshua@the-britains.com
License: UNKNOWN
Platform: UNKNOWN
Classifier: Programming Language :: Python :: 3
Classifier: License :: OSI Approved :: MIT License
Classifier: Operating System :: OS Independent
